<?xml version="1.0" encoding="utf-8"?><resources xmlns:xliff="urn:oasis:names:tc:xliff:document:1.2">
    <string name="description_ip_call_action">  <xliff:g example="John Smith" id="nameOrNumber">%1$s</xliff:g> IP-hívása </string>
    <string name="select_account">"Fiók kiválasztása"</string>
    <string name="all_accounts">"Minden fiók"</string>
    <string name="imei_invalid">Érvénytelen</string>
    <string name="conf_call_member_list">Tagok listája</string>
    <string name="conf_call_participant_answered">Hívás fogadva</string>
    <string name="conf_call_participant_missed">"Nem fogadott"</string>
<string name="calls_over_wifi">A hívások Wi-Fi-n át mennek</string>
<string name="connect_to_wifi">Csatlakozva Wi-Fi-re a hívásokhoz</string>
<string name="wfc_notification_summary">Érintse meg a beállításokhoz</string>
<string name="wfc_notification_summary_fail">Érintse meg az elérhető hálózatokhoz</string>
<string name="can_not_switch_account_during_call">Nem lehet átváltani a hívásokhoz preferált SIM kártyát hívás közben.</string>
<string name="can_not_switch_account_temporarily">Átmenetileg nem lehet átváltani a hívásokhoz preferált SIM kártyát.</string>
</resources>
