<?xml version="1.0" encoding="utf-8"?><resources xmlns:xliff="urn:oasis:names:tc:xliff:document:1.2">
<string name="ring_summary">घण्टी</string>
<string name="ring_vibrate_summary">घण्टी र कम्पन</string>
<string name="silent_summary">साइलेन्ट मात्र</string>
<string name="meeting_summary">कम्पन১ मात्र</string>
<string name="outdoor_summary">सबैभन्दा ठूलो घण्टी र कम्पन১</string>
<string name="audio_profile_reset">प्रोफाइल रिसेट गर्नुहोस</string>
<string name="audio_profile_add">प्रोफाइल थप्नुहोस्</string>
<string name="audio_profile_enable">सक्षम गर्नुहोस्</string>
<string name="audio_profile_rename">पुनः नामकरण</string>
<string name="audio_profile_delete">मेट्नुहोस्</string>
<string name="audio_profile_message_reset">सबै अडियो प्रोफाइल सेटिङहरू पूर्वनिर्धारितमा रिसेट हुनेछन्</string>
<string name="audio_profile_message_rename">कृपया नयाँ प्रोफाइल नाम राख्नुहोस्</string>
<string name="audio_profile_message_name_error">नाम पहिले राखेको देखिन्छ</string>
<string name="audio_profile_message_name_length_wrong">नाममा कम्तिमा एक वर्ण समावेश हुनुपर्छ</string>
<string name="audio_profile_message_delete">
<xliff:g id="profile">%s</xliff:g> प्रोफाइल मेटाइनेछ</string>
<string name="audio_profile_message_overflow">तपाईंलाई मात्र 6 कस्टम১ प्रोफाइलहरू थप्न अनुमति छ</string>
<string name="audio_profile_category_custom_title">प्रयोगकर्ता निर्धारित प्रोफाइलहरू</string>
<string name="audio_profile_category_predefine_title">सामान्य टोन सेटिङहरू</string>
<string name="audio_profile_error">त्रुटि</string>
<string name="audio_profile_others">सूचना र अन्य</string>
<string name="general_settings_title">साधारण</string>
<string name="silent_settings_title">मौन</string>
<string name="meeting_settings_title">बैठक</string>
<string name="outdoor_settings_title">बाहिर</string>
<string name="sound_category_feedback_title">प्रणाली</string>
<string name="sound_category_calls_title">आगमन कलहरू</string>
<string name="voice_call_title">भ्वाइस कल रिङ्गटोन</string>
<string name="voice_call_summary">तपाईंको पूर्वनिर्धारित भ्वाइस कल रिङ्गटोन सेट गर्नुहोस्</string>
<string name="video_call_title">भिडियो कल रिङ्गटोन</string>
<string name="video_call_summary">तपाईंको पूर्वनिर्धारित भिडियो कल रिङ्गटोन सेट गर्नुहोस्</string>
<string name="sip_call_title">SIP कल रिङ्गटोन</string>
<string name="sip_call_summary">तपाईंको पूर्वनिर्धारित SIP कलहरू रिङ्गटोन सेट गर्नुहोस्</string>
<string name="Phone_vibrate_summary">आगमन कलहरूमा यन्त्रहरू कम्पन गर्नुहोस्</string>
<string name="vibrate_title">कम्पन</string>
<string name="audio_profile_settings_title">अडियो प्रोफाल</string>
<string name="audio_profile_bes_loudness_summary">स्पीकर भोल्युम১ बुस्टर</string>
<string name="sound_enhancement_title">आवाज बृद्दि</string>
<string name="music_plus_summary">इयरफोनको लागि अडियो बृद्दिगर्ने</string>
<string name="lossless_title">दोषरहित Bluetooth मोड</string>
<string name="lossless_summary">उच्च गुणस्तर Bluetooth संगीत</string>
<string name="lossless_connect_summary">दोषरहित Bluetooth मोड अन गरिदाँ Wi-Fi प्रभावित हुनेछ। जसरी पनि सक्षम पार्ने?</string>
<string name="lossless_on">दोषरहित Bluetooth मोड सक्षम पारियो</string>
<string name="lossless_playing">दोषरहित Bluetooth मोड सक्षम पारियो</string>
<string name="lossless_toastmessage">सिस्टम आवाज फोन स्पीकरबाट प्ले हुनेछ</string>
<string name="lossless_volume_max">मिडिया भोल्युम अधिकतममा वृद्धि गर्नुहोस्</string>
<string name="lossless_cannot_found_device">कुनै दोषरहित Bluetooth यन्त्रहरू फेला परेनन्</string>
<string name="audio_profile_bes_surround_title">BesSurround</string>
<string name="audio_profile_bes_surround_summary">अडियो परिवेश</string>
<string name="audio_profile_bes_surround_mode_movie">चलचित्र मोड</string>
<string name="audio_profile_bes_surround_mode_music">संगीत मोड</string>
<string name="zen_mode_option_title_novoice">जब सूचनाहरू आउँछ</string>
<string name="wifi_no_cert_for_wapi">हाल जडान भैरहेको AP को लागि प्रमाणीकरण फेला परेन</string>
<string name="sim_slot">SIM स्लट</string>
<string name="eap_sim_slot_0">SIM स्लट 1</string>
<string name="eap_sim_slot_1">SIM स्लट 2</string>
<string name="eap_sim_aka_airplanemode">कृपया EAP-SIM/AKA प्रयोग गर्न विमान১ मोड बन्द गर्नुहोस्</string>
<string name="eap_sim_aka_no_sim_error">EAP-SIM/AKA प्रयोग गर्न तपाईंले सिम कार्ड घुसाउनु पर्छ</string>
<string name="eap_sim_aka_no_sim_slot_selected">EAP-SIM/AKA प्रयोग गर्न तपाईंले सिम स्लट चयन गर्नुपर्छ</string>
<string name="wifi_security_wapi_certificate">WAPI प्रमाणपत्र</string>
<string name="wapi_user_certificate">प्रयोगकर्ता प्रमाणपत्र</string>
<string name="wapi_as_certificate">ASE प्रमाणपत्र</string>
<string name="wifi_hex_password">हेक्साडेसिमल पासवार्ड।</string>
<string name="wifi_WEP_transmit_key">ट्रान्स्मिट कुञ्जी</string>
<string name="wifi_WEP_secury_key">सुरक्षा कुञ्जी</string>
<string name="wifi_tether_auto_disable_title">Wi-Fi हटस्पट अन राख्नुहोस्</string>
<string name="wifi_tether_auto_channel_text">स्वत</string>
<string name="wifi_tether_auto_channel_width_text">स्वत: 20/40 MHz</string>
<string name="wifi_channel">अधिमान्य च्यानल</string>
<string name="wifi_channel_width">ब्याण्डविथ</string>
<string name="wifi_advanced_ipv4_address_title">IPv4 ठेगाना</string>
<string name="wifi_advanced_ipv6_address_title">IPv6 ठेगाना</string>
<string name="wifi_ipv4_address">IPv4 ठेगाना</string>
<string name="wifi_ipv6_address">IPv6 ठेगाना</string>
<string name="wifi_ap_auto_join_available">स्वत; स्वीच</string>
<string name="wifi_ap_auto_join_available_summary">जडान भएको बेला जोडिन स्क्यान गरिरहदाँ राम्रो Wi-Fi नेटवर्क स्वत: छान्नुहोस्</string>
<string name="wifi_tether_setting_title">आधारभूत सेटिङहरू</string>
<string name="wifi_tether_wps_connect_title">WPS जडान</string>
<string name="wifi_tether_wps_connect_summary">अगाडि बढ्न১ चयन गरिएको Wi-Fi सुरक्षित गरिएको सेटअप मोड</string>
<string name="wifi_tether_wps_pin_error">अमान्य PIN</string>
<string name="wifi_tethering_title">पोर्टेबल Wi-Fi हटस्पट</string>
<string name="wifi_ap_wps_dialog_title">WPS जडान</string>
<string name="wifi_ap_wps_mode_title">WPS मोड</string>
<string name="wifi_ap_wps_pin_title">ग्राहकबाट PIN टाइप गर्नुहोस्</string>
<string name="wifi_ap_reset_OOB_title">नेटवर्क SSID, सुरक्षा र पासवर्ड पूर्वनिर्धारितको रूपमा रिसेट गर्नुहोस् ( WPS को लागि आउट-अफ-बक्स कन्फिगुरेसन )</string>
<string name="wifi_ap_reset_OOB">OOB रिसेट गर्नुहोस्</string>
<string name="wifi_ap_max_connection_title">अधिक्तम जडानहरू</string>
<string name="wifi_ap_connected_title">जडान भएका प्रयोगकर्ताहरू</string>
<string name="wifi_ap_blocked_title">ब्लक गरिएका प्रयोगकर्ताहरू</string>
<string name="wifi_ap_client_block_title">ब्लक गर्नुहोस्</string>
<string name="wifi_ap_client_unblock_title">ब्लक रद्द गर्नुहोस्১</string>
<string name="wifi_ap_client_details_title">विवरणहरू</string>
<string name="wifi_ap_client_mac_label">MAC ठेगाना:</string>
<string name="wifi_ap_client_ip_label">IP ठेगाना:</string>
<string name="wifi_ap_bandwidth_title">ब्याण्डविथ उपयोग</string>
<string name="wifi_ap_bandwidth_enable">ब्याण्डविथ थ्रोटलिङ सक्षम पार्नुहोस्</string>
<string name="wifi_ap_bandwidth_chart_title">रिअल टाइम डाटा गति</string>
<string name="wifi_ap_bandwidth_chart_summary">तपाईंको फोनद्वारा मापन गरिएको, तपाईंको बाहकको डाटा गति लेखा फरक हुनसक्छ।</string>
<string name="wifi_wps_fail_error">Wi-Fi सुरक्षित गरिएको सेटअप असफल भयो, फेरि प्रयास गर्नुहोस्।</string>
<string name="wifi_ap_title">तथ्याङ्क</string>
<string name="wifi_ap_time_duration">अवधिको समय:<xliff:g id="time">%1$s</xliff:g>
</string>
<string name="wifi_ap_total_data">प्रयोग गरिएको कूल डाटा:<xliff:g id="time">%1$s</xliff:g>
</string>
<string name="wifi_ap_no_connected">0 जडान भएको प्रयोगकर्ता</string>
<string name="wifi_ap_no_blocked">0 ब्लक गरिएको प्रयोगकर्ता</string>
<string name="wifi_ap_help_title">मद्दत</string>
<string name="help_document">1. तपाईंको यन्त्र पोर्टेबल Wi-Fi हटस्पट बिशेषता मार्फत इन्टरनेट पहुँच बिन्दुको रूपमा प्रयोग गर्न सकिन्छ। तपाईंको यन्त्रमा बाह्य यन्त्रहरू जडान हुनसक्छ र तपाईंको मोबाइल डाटा जडानमा इन्टरनेट पहुँच गर्छन।\n2.पोर्टेबल Wi-Fi हटस्पट बिशेषता प्रयोग गर्नु पहिले, मोबाइल डाटा सक्षम पार्नुहोस्। एप्लिकेसन डाटा शुल्कहरू लागू हुनसक्छ।\n3. पोर्टेबल Wi-Fi हटस्पट प्रयोगले धेरै शक्ति उपयोग गर्नेछ।</string>
<string name="beam_mgmt_tab_download_title">"प्राप्त भएको"</string>
<string name="beam_mgmt_tab_upload_title">"पठाइएको"</string>
<string name="beam_share_mgmt_notification_ticker">Beam साझा इतिहास</string>
<string name="beam_share_mgmt_notification_title">Beam साझा इतिहास</string>
<string name="beam_share_mgmt_notification_message">Beam साझा इतिहास हेर्न चयन गर्नुहोस्।</string>
<string name="beam_share_mgmt_tab_menu_clear">" सबै खाली गर्नुहोस्"</string>
<string name="beam_share_open_file_dialog_title">फाइल खोल्न सकिन्न</string>
<string name="beam_share_open_file_unsupported_message">फाइल ढाँचा১ समर्थित छैन।</string>
<string name="beam_share_open_file_not_found_message">"फाइल फेला परेन: <xliff:g id="file_name">%1$s</xliff:g>
</string>
<string name="beam_share_transfer_fail_dialog_title">Beam असफल भयो</string>
<string name="beam_share_resend_dialog_message">"<xliff:g id="file_name">%1$s</xliff:g> सफलतापूर्वक पठाइएन।"</string>
<string name="beam_share_resend_dialog_ok_button">पुन: प्रयास गर्नुहोस्</string>
<string name="beam_share_show_received_files_menu">प्राप्त भएका फाइलहरू देखाउनुहोस्</string>
<string name="beam_share_history_title">Beam साझा इतिहास</string>
<string name="beam_share_clear_confirm_dialog_title">सबै खाली गर्नुहोस्</string>
<string name="beam_share_clear_confirm_dialog_message">सबै इतिहास मेटाउने?</string>
<string name="beam_share_receive_fail_dialog_message">"<xliff:g id="file_name">%1$s</xliff:g> सफलतापूर्वक प्राप्त भएन।"</string>
<string name="beam_share_clear_item_dailog_title">मेट्नुहोस्</string>
<string name="beam_share_clear_item_dailog_message">वस्तु मेटाइनेछ।</string>
<string name="nfc_p2p_mode">P2P मोड</string>
<string name="nfc_p2p_mode_summary">एप सामग्री पठाउनुहोस् वा प्राप्त गर्नुहोस्</string>
<string name="nfc_tag_mode_category">ट्याग मोड</string>
<string name="nfc_rw_tag_title">ट्याग पढाइ र लेखाइ</string>
<string name="nfc_rw_tag_summary">बाट पढ्नुहोस् वा ट्यागमा लेख्नुहोस्</string>
<string name="nfc_card_emulation_category_title">कार्ड इमुलेसन मोड</string>
<string name="nfc_card_emulation">कार्ड इमुलेसन</string>
<string name="card_emulation_settings_category_title">उपलब्ध सुरक्षा तत्व</string>
<string name="card_emulation_settings_no_element_found">सुरक्षा तत्व उपलब्ध छैन।</string>
<string name="card_emulation_settings_off_text">उपलब्ध सुरक्षा तत्वहरू हेर्न, कार्ड इमुलेसन अन गर्नुहोस्।</string>
<string name="card_emulation_turning_off_text">कार्ड इमुलेसन बन्द हुदै...</string>
<string name="card_emulation_turning_on_text">कार्ड इमुलेसन अन हुदै...</string>
<string name="card_emulation_switch_error_title">त्रुटि</string>
<string name="card_emulation_switch_error_message">
<xliff:g id="card_mode">%1$s</xliff:g> मा बदल्न১ असफल भयो।</string>
<string name="card_emulation_sim_not_supported_message">
<xliff:g id="sim_description">%1$s</xliff:g> ले NFC कार्ड इमुलेसन प्रकार्यलाई समर्थन गर्दैन।</string>
<string name="card_emulation_two_sim_not_supported_message">SIM1,SIM2 ले NFC कार्ड इमुलेसन प्रकार्यलाई समर्थन गर्दैनन्।</string>
<string name="nfc_hce_pay_summary">तपाईंको यन्त्रलाई क्रेडिट कार्ड वा ट्याप गरि तिर्नुहोस् सहितको Google वालेटको रूपमा प्रयोग गर्नुहोस्</string>
<string name="wfd_change_resolution_menu_title">रिजोलुसन परिवर्तन गर्नुहोस्</string>
<string name="wfd_sink_summary">अन्यहरूद्वारा फेला पार्न सक्ने</string>
<string name="wfd_device_category">यन्त्रहरू सूची</string>
<string name="wfd_sink_toast_enjoy">अन्य यन्त्रबाट स्क्रिन कास्टिङको आनन्द लिनुहोस्</string>
<string name="wfd_sink_toast_disconnect">कास्ट स्क्रिन विच्छे১द भयो</string>
<string name="wfd_sink_disconnecting">जडान विच्छेद गर्दै...</string>
<string name="wfd_sink_guide_btn">ओके</string>
<string name="wfd_sink_guide_title">कसरी बन्द गर्ने?</string>
<string name="wfd_sink_guide_content">अन्य यन्त्रबाट कास्ट स्क्रिन बन्द गर्न स्क्रिनलाई <xliff:g id="seconds">%s</xliff:g> सेकेण्ड टच गरि होल्ड गर्नुहोस्।</string>
<string name="mtp_transfer_unmount_error_text">फाइल स्थानान्तरण भैरहेको बेला SD कार्ड अनमाउण्ट गर्न सकिदैन</string>
<string name="mtp_transfer_erase_error_text">फाइल स्थानान्तरण भैरहेको बेला SD कार्ड मे১टाउन सकिदैन</string>
<string name="launch_error">एप्लिकेसन लन्च हुनसकेन</string>
<string name="dlg_confirm_unmount_usb_title" product="default">USB भण्डारण अनमाउण्ट गर्नुहोस्?</string>
<string name="dlg_confirm_unmount_usb_text" product="default">यदि तपाईंले USB भण्डारणलाई अनमाउण्ट गर्नुभयो भने, तपाईंले प्रयोग गरिरहनु भएको केही एप्सहरू रोकिनेछन् र तपाईंले USB भण्डारणलाई रिमाउण्ट नगर्दासम्म अनुपलब्ध हुनसक्छन्।</string>
<string name="dlg_error_unmount_usb_text" product="default">USB भण्डारण अनमाउन्ट गर्न सकिएन। पछि फेरि प्रयास गर्नुहोस्।</string>
<string name="unmount_usb_inform_text" product="default">USB भण्डारणलाई अनमाउण्ड गरिनेछ।</string>
<string name="sd_eject_usbstorage" product="default">USB भण्डारण अनमाउण्ट गर्नुहोस्</string>
<string name="sd_eject_usbstorage_summary" product="default">USB भण्डारणलाई अनमाउण्ट गर्नुहोस् जसबाट तपाईंले यसलाई सुरक्षितचरूपमा हटाउन सक्नुहुन्छ</string>
<string name="sd_mount_usbstorage" product="default">USB भण्डारण माउण्ट गर्नुहोस्</string>
<string name="sd_insert_usb_summary" product="default">माउण्ट गर्नको लागि USB भण्डारण घुसाउनुहोस्</string>
<string name="usb_ums_title">USB भण्डारण</string>
<string name="usb_ums_summary">"XP सुझाव गरिन्छ। तपाईंलाई आफ्नो कम्प्युटर र आफ्नो एन्ड्रोइड यन्त्र बीच फाइल हस्तान्तरण गर्न दिन्छ১।"</string>
<string name="usb_charge_title">चार्ज मात्र</string>
<string name="usb_connect_as_cdrom_category">CD-ROM को रूपमा जडान गर्नुहोस्</string>
<string name="usb_charge_summary">सबै USB प्रकार्यहरू बन्द गर्नुहोस्। तपाईंलाई आफ्नो USB चार्जिङ गति बढाउन र पावर उपयोग घटाउन दिन्छ।১</string>
<string name="akp_installer_settings_title">APK स्थापक</string>
<string name="akp_installer_settings_summary">फोन भण्डारण र SD कार्डबाट तपाईंको APK स्थापन गर्नुहोस्</string>
<string name="usb_bicr_title">बिल्ट-इन CD-ROM</string>
<string name="usb_bicr_summary">केही उपयोगी सफ्टवेयर समावेश भएका यथार्थ CD-ROM देखाउनुहोस्।</string>
<string name="select_memory">पूर्वनिर्धारित लेख्ने डिस्क</string>
<string name="dlg_mount_external_sd_title" product="default">SD कार्ड माउण्ट गर्ने?</string>
<string name="dlg_mount_external_sd_summary" product="default">यदि तपाईंले SD कार्ड माउण्ट गर्नुहुन्छ भने, तपाईंले प्रयोग गरिरहनु भएको केही एप्स रोकिनेछ।</string>
<string name="hdmi_settings">HDMI सेटिङहरू</string>
<string name="hdmi_settings_summary">HDMI कन्फिगर गर्न टच गर्नुहोस्</string>
<string name="hdmi_audio_toggler">अडियो</string>
<string name="hdmi_video_toggler">भिडियो</string>
<string name="hdmi_video_resolution">भिडियो रिजोलुसन</string>
<string name="hdmi_auto">स्वत</string>
<string name="hdmi_scale_control">भिडियो स्केल आकार১ सेटिङहरू</string>
<string name="hdmi_scale_no_scale">स्केलिङ छैन</string>
<string name="hdmi_scale_scale_down">स्केल डाउन <xliff:g id="scale_percent">%s</xliff:g>%%</string>
<string name="hdmi_audio_output">अडियो आउटपुट</string>
<string name="hdmi_audio_output_stereo">स्टेरियो</string>
<string name="hdmi_audio_output_multi_channel">बहु-च्यानल</string>
<string name="landscape_launcher_title">ल्याण्डस्केप लन्चर </string>
<string name="landscape_launcher_none">कुनै पनि होइन</string>
<string name="display_settings_scences_title">दृष्यहरू</string>
<string name="default_name">पूर्वनिर्धारित</string>
<string name="custom_theme_name">नयाँ [%1$s]</string>
<string name="loading">लोड हुँदैछ...</string>
<string name="auto_backlight_title">अटोमेटिक ब्याकलाइट</string>
<string name="auto_backlight_summary">पावर बचत गर्न ब्याकलाइटलाई स्वचालित रूपमा अनुकूलन गर्नुहोस्</string>
<string name="display_personalize">निजीकरण</string>
<string name="display_default">प्रदर्शन गर्नुहोस्</string>
<string name="clear_motion_summary">भिडियो स्पस्टता बृद्दिकर्ता</string>
<string name="on_text">अन</string>
<string name="off_text">अफ</string>
<string name="voice_unlock_backup_info_summary">जब भ्वाइस अनलकले तपाईंलाई पहिचान गर्न सक्दैन, तपाईं कसरी अनलक गर्न चाहनुहुन्छ?</string>
<string name="unlock_set_unlock_mode_voice_weak">भ्वाइस हनलक</string>
<string name="mtk_lock_screen_notifications_title">लक स्क्रिन सूचनाहरू</string>
<string name="lock_screen_notifications_summary">लक स्क्रिनमा सूचनाहरू देखाउनुहोस्</string>
<string name="lock_screen_style_title">लक स्क्रिन स्वरूप</string>
<string name="current_suffix">(हाल)</string>
<string name="lockscreen_style_default_desc">"लक स्क्रिनको एप्लिकेसनमा तिव्र पहुँच हुनुहुोस्"</string>
<string name="security_not_set">सुरक्षा सेट छैन</string>
<string name="voice_ui_title">भ्वाइस नियन्त्रण</string>
<string name="pch_toggle_title">GPRS स्थानान्तर अधिमान्य मोड</string>
<string name="pch_data_prefer_summary_off">डाटा प्राथमिक गर्नुहोस्</string>
<string name="pch_call_prefer_summary_on">कलिङ प्राथमिक गर्नुहोस्</string>
<string name="pch_warning_message">डाटा प्रसारण दर घट्नेछ।</string>
<string name="tethered_ipv6_title">हटस्पट र टिथरिङ सेटिङहरू</string>
<string name="tethered_ipv4v6">(IPv6 उपलब्ध)</string>
<string name="tethered_ipv6">(मात्र IPv6 उपलब्ध)</string>
<string name="tethered_ipv4">(IPv6 अनुपलब्ध)</string>
<string name="tethering_apn_settings_title">APN सेटिङहरू</string>
<string name="tethering_apn_settings_summary">टिथरिङको लागि APN कन्फिगर गर्नुहोस्</string>
<string name="usb_tether_type_title">USB टिथरिङ प्रकार</string>
<string name="usb_tethering_select_version">PC प्रणाली संस्करण चयन गर्नुहोस्</string>
<string name="apn_port_warning">पोर्ट मान 1-65535 हुनैपर्छ!</string>
<string name="apn_predefine_change_dialog_notice">बचत गर्न तपाईं निश्चित हुनुहुन्छ? पूर्वनिर्धारित APNs मा परिवर्तनले जडान समस्या ल्याउनसक्छ!"</string>
<string name="lockdown_vpn_already_connected">सधै अन राख्नुहोस् VPN जडानको लागि पहिले नै सक्षम छ।</string>
<string name="schedule_power_on_off_settings_title">स्वत: पावर अन र अफ</string>
<string name="ipo_title">तिव्र बुट</string>
<string name="ipo_summary_on">तिव्र बुट अक्षम पार्नुहोस्</string>
<string name="ipo_summary_off">तिव्र बुट सक्षम पार्नुहोस्</string>
<string name="hotknot_explained_description">स्क्रिनले अर्को यन्त्र टच गरेको बेला डाटा साटासाट गर्न अनुमति दिनुहोस्</string>
<string name="mouse_primary_button_title">प्राथमिक र सहायक बटनहरू स्वीच गर्नुहोस्</string>
<string name="mouse_primary_button_dialog_title">प्राथमिक बटन स्वीच गर्नुहोस्</string>
<string name="double_click_title">दोहोरो क्लिक गति</string>
<string name="test_area">जाँच क्षेत्र:</string>
<string name="double_click_tip">यहाँ दुईपटक क्लिक गर्नुहोस्</string>
<string name="hetcom_setting_title">टर्बो डाउनलोड</string>
<string name="bluetooth_advanced_settings">उच्च श्रेणीको सेटिङहरू</string>
<string name="bluetooth_profile_ftp">फाइल स्थानान्तर</string>
<string name="bluetooth_ftp_profile_summary_use_for">फाइल स्थानान्तरणको लागि प्रयोग गर्नुहोस्</string>
<string name="bluetooth_ftp_profile_summary_connected">"फाइल स्थानान्तरमा जडान छ"</string>
<string name="gps_time_sync_attention_gps_on">GPS फिक्स प्राप्त गर्न धेरैमा 1 मिनेट लाग्नेछ। त्यसबाहेक, कमजोर वातावरणीय संकेतको कारणले GPS ले समय उपलब्ध गराउन असफल हुनसक्छ।\n\nके तपाईं GPS बाट उपलब्ध समय प्रयोग गर्न निश्चित हुनुहुन्छ?</string>
<string name="gps_time_sync_attention_gps_off">GPS बाट उपलब्ध हुने समय प्रयोग गर्न, तपाईंले पहिले GPS सक्षम पार्नुपर्छ। त्यसपछी यसले GPS फिक्स प्राप्त गर्न धेरैमा 1 मिनेट लिनेछ। त्यसबाहेक, कमजोर वातावरणीय संकेतको कारणले GPS ले समय उपलब्ध गराउन असफल हुनसक्छ। \n\nके तपाईंले अहिले GPS सक्षम पार्ने र GPS बाट उपलब्ध हुने समयको लागि प्रतिक्षा गर्ने?</string>
<string name="drm_settings_title">DRM रिसेट</string>
<string name="drm_settings_summary">सबै DRM लाइसेन्सहरू मेटाउनुहोस्</string>
<string name="drm_reset_dialog_msg">यो कार्यले यस यन्त्रको सबै लाइसेन्सहरू मेटाउनेछ। जारी राख्नुहोस्?</string>
<string name="drm_reset_toast_msg">लाइसेन्सहरू सफलतापूर्वक मेटाइयो।</string>
<string name="launch_main_label">एप्लिकेसन लन्च गर्नुहोस्</string>
<string name="launch_main">मूख्य क्रियाक्लापबाट एप्लिकेसन लन्च गर्नुहोस्</string>
<string name="launch_activitie">लन्च गर्नुहोस्</string>
<string name="move_app_to_where">
<xliff:g id="location">%s</xliff:g> मा जानुहोस्</string>
<string name="bg_power_saving_title">स्ट्याण्डबाइ स्मार्ट पावर बचत</string>
<string name="bg_power_percent_title">ब्याट्री प्रतिशत देखाउनुहोस्</string>
<string name="bg_power_percent_summary">स्थिति पट्टिमा बाँकी ब्याट्री प्रतिशत देखाउनुहोस्</string>
<string name="mtk_datausage_overview_tab">संक्षिप्त विवरण</string>
<string name="mtk_datausage_overview_wifi_today">आज</string>
<string name="mtk_datausage_overview_wifi_total">जम्मा</string>
<string name="mtk_datausage_overview_mobile_title">मोबाइल</string>
<string name="mtk_datausage_overview_mobile_usage">
<xliff:g id="limit">%s</xliff:g> को <xliff:g id="actual">%s</xliff:g>
</string>
<string name="mtk_datausage_overview_mobile_usage_warning">सीमा भन्दा बाहिर <xliff:g>%s</xliff:g>
</string>
<string name="data_saving_title">डाटा बचत</string>
<string name="status_imei_slot1">IMEI(सट1)</string>
<string name="status_imei_slot2">IMEI(सट2)</string>
<string name="custom_build_version">अनुकूल निर्माण संस्करण</string>
<string name="mota_system_update_summary">अपडेटहरू चेक गर्नुहोस्</string>
<string name="software_updates_more_title">सफ्टवेयर अपडेट</string>
<string name="software_updates_more_summary">नयाँ संस्करण सफ्टवेयर चेक गर्नुहोस्</string>
<string name="sim_cards_celluar_data_dialog_title">सेलुलर डाटा प्रयोग गर्न SIM कार्ड छान्नुहोस्</string>
<string name="sim_cards_data_sms_dialog_title">SMS सन्देशहरू प्रयोग गर्न SIM कार्ड छान्नुहोस्</string>
<string name="sim_cards_calls_dialog_title">फोन कलहरू गर्न खाता छान्नुहोस्</string>
<string name="sim_cards_other_calls_dialog_title">अर्को खाता छान्नुहोस्</string>
<string name="sim_cards_other_calls_item_title">अर्को खाता</string>
<string name="data_connection_progress_message">अर्को SIM कार्डमा स्वीच गरिनु पुरा हुन लगभग 10 सेकेण्ड लाग्नेछ। कृपया पर्खनुहोस्।</string>
<string name="gemini_sim_mode_progress_activating_message">सक्रिय हुदै\u2026</string>
<string name="gemini_sim_mode_progress_deactivating_message">निष्क्रिय हुदै\u2026</string>
<string name="simui_intenet_call">इन्टरनेट कल</string>
<string name="imei_information_title">IMEI जानकारी</string>
<string name="imei_information_summary">IMEI सँग सम्बन्धित जानकारी</string>
<string name="slot_number">(Slot <xliff:g id="slot_num">%1$d</xliff:g>)</string>
<string name="sim_info_editor_color">पृष्ठभूमी रङ्ग</string>
<string name="sim_cards_notify_title">SIM कार्ड परिवर्तन भयो</string>
<string name="sim_cards_notify_summary">अधिमान्यहरू सेट् गर्न टच गर्नुहोस्।</string>
<string name="no_sim_cards_notify_title">कुनै SIM कार्ड प्ल्ग इन छैन</string>
<string name="cellular_data_notify_title">सेलुलर डाटा अनुपलब्ध छ</string>
<string name="cellular_data_notify_summary">डाटा SIM कार्ड सेट गर्न टच गर्नुहोस्।</string>
<string name="sms_vibrate_summary">नयाँ SMS को लागि यन्त्र कम्पन गर्छ</string>
<string name="default_data_switch_err_msg1">कल अवधिमा अधिमान्य SIM कार्ड सेलुलर डाटामा स्वीच हुनसक्दैन।</string>
<string name="two_cdma_dialog_msg">दुईवटा CDMA SIM कार्ड देखिन्छ। मात्र स्लट 1 ले CDMA कार्ड लिन सक्छ।</string>
<string name="voice_call_sim2_title">SIM 2 फोनघण्टी</string>
<string name="ringtone_sim2_title">SIM 2 फोनघण्टी</string>
<string name="wfc_quick_toggle_title">Wi-Fi कलिङ</string>
<string name="Help">मद्दत</string>
<string name="Tutorials">टुटोरिअल</string>
<string name="Top_questions">सर्वश्रेष्ठ प्रश्नहरू</string>
<string name="Wifi_wfc_dialog_title">Wi-Fi कलिङ</string>
<string name="Wifi_wfc_dialog_top_wording">तपाईं अहिले Wi-Fi नेटवर्कमा जडान हुनुहुन्छ</string>
<string name="Wifi_wfc_dialog_bottom_wording">Wi-Fi नेटवर्कमा जडान भएपछि जब तपाईंले यो संकेत तपाईंको स्क्रिनको माथि देख्नुहुन्छ, तपाईंले Wi-Fi बाट कलहरू गर्न र सन्देशहरू पठाउन सक्षम हुनुहुन्छ।</string>
<string name="Skip">छोड्नुहोस्</string>
<string name="Learn_more">थप सिक्नुहोस्</string>
<string name="Next">अर्को</string>
<string name="Switch_not_in_use_string">स्वीच अल्पकालीनरूपमा अनुपलब्ध छ। कृपया पछि पुन: प्रयास गर्नुहोस्।</string>
<string name="Done">सम्पन्न भयो</string>
<string name="Wfc_questions">Wi-Fi कलिङ प्रश्नहरू</string>
<string name="Wfc_off_summary">अक्षम बनाइयो</string>
<string name="wfc_on_summary">Wi-Fi कलिङ अन</string>
<string name="connection_preference">जडान अधिमान्यहरू</string>
<string name="WiFi_preferred">अधिमना्य गरिएको Wi-Fi</string>
<string name="Cellular_network_preferred">अधिमान्य गरिएको सेलुलर नेटवर्क</string>
<string name="Never_use_cellular_network">सेलुलर नेटवर्क कहिल्यै प्रयोग नगर्नुहोस्</string>
<string name="WiFi_preferred_summary">कलहरूको लागि Wi-Fi प्रयोग गर्नुहोस्। यदि WI-FI अनुपलब्ध छ भने, सेलुलर नेटवर्क प्रयोग गर्नुहोस्। (पूर्वनिर्धारित)</string>
<string name="Cellular_network_preferred_summary">कलहरूको लागि सेलुलर नेटवर्क प्रयोग गर्नुहोस्। यदि सेलुलर नेटवर्क नभएमा, Wi-Fi प्रयोग गर्नुहोस्।</string>
<string name="Never_use_cellular_network_summary">कलहरूको लागि Wi-Fi मात्र प्रयोग गर्नुहोस्। उपलब्ध भएता पनि, सेलुलर नेटवर्क प्रयोग नगर्नुहोस्।</string>
<string name="no_sim_present_error">SIM अवस्थित छैन</string>
<string name="inavlid_sim_error">त्रुटि 05: अमान्य SIM</string>
<string name="airplane_mode_on">जहाजयात्रा मोड अन छ</string>
<string name="cellular_prefered_summary">सेलुलर तपाईमको अधिमान्य जडान मोड हो</string>
<string name="wifi_off_summary">Wi-Fi बन्द छ</string>
<string name="not_connected_to_wifi_summary">Wi-Fi मा जडान छैन</string>
<string name="poor_wifi_signal_summary">कमजोर Wi-Fi संकेत</string>
<string name="wfc_enabling_summary">सक्षम हुदै...</string>
<string name="wfc_disabling_summary">हक्षम हुदै...</string>
<string name="wfc_ready_for_calls_summary">कलको लागि तयार</string>
<string name="wfc_unknown_error_summary">अज्ञात त्रुटि</string>
<string name="wfc_tutorial_heading">Wi-Fi कलिङको बारेमा सबै जान्नुहोस्</string>
<string name="wfc_tutorial_content_first_page">Wi-Fi कलिङले तपाईंको अपूर्ण कभरेजलाई बिदाइ गर्छ। Wi-Fi कलिङबाट तपाईंले Wi-Fi नेटवर्कमा तपाईंको हालको टि-मोबाईल योजना प्रयोग गरी सन्देशहरू पठाउन र प्राप्त गर्नसक्नुहुन्छ। Wi-Fi कलिङको लागि कुनै बिशेष सेटअप आवश्यक छैन। शुरूवात गर्न सेटिङ मेनुबाट तारविहीन र नेटवर्कहरूमा जानुहोस् र Wi-Fi नेटवर्कमा जडान गर्नुहोस्।</string>
<string name="wfc_tutorial_content_second_page_part1">एकपटक तपाईंले Wi-Fi कलिङ नेटवर्क स्थिति पट्टिमा देखेपछि, तपाईंको फोन Wi-Fi कलिङको लागि तयार हुन्छ।</string>
<string name="wfc_tutorial_content_second_page_part2">১Wi-Fi कलमा रहिरहन, Wi-Fi नेटवर्क रेन्जमा रहनुहोस्। तपाईं रेन्ज भन्दा बाहिर गएको कारणले कल असफल भएको तपाईंलाई थाहा दिन तपाईंले बीपको आवाज र स्क्रिन सन्देश प्राप्त गर्नुहुनेछ।</string>
<string name="wfc_incorrect_sim_alert_title">त्रुटि 05: अमान्य SIM कार्ड</string>
<string name="wfc_invalid_sim_alert_message">महत्वपूर्ण सूचना\nWi-Fi कलिङ सक्षमताको लागि तपाईंको SIM कार्ड अपडेट गरिनुपर्छ। कृपया ग्राहक स्याहारमा पुग्न टि-मोबाइल पसलमा जानुहोस् वा आफ्नो फोनबाट 611 डायल गर्नुहोस्।</string>
<string name="ok_string">ओके</string>
<string name="storage_internal_storage_title">आन्तरिक भण्डारण</string>
<string name="storage_cleaner_preference_title">भण्डारण क्लीनर</string>
<string name="mira_vision_title">प्रदर्शन प्रभाव</string>
</resources>
